peegee.py
peegee-0.2.3.dist-info/LICENSE
peegee-0.2.3.dist-info/METADATA
peegee-0.2.3.dist-info/WHEEL
peegee-0.2.3.dist-info/top_level.txt
peegee-0.2.3.dist-info/RECORD
